{
  "extends": ["tslint-config-airbnb", "tslint-react", "tslint-immutable"],
  "rules": {
    "indent": [true, "spaces"],
    "import-name": false,
    "semicolon": [false],
    "jsx-no-lambda": false,
    "jsx-no-multiline-js": false,
    "ter-indent": [
      true,
      4
    ],
    "trailing-comma": false,
    // This rule is here for now because of https://github.com/palantir/tslint-react/issues/120
    "variable-name": [true, "ban-keywords", "check-format", "allow-pascal-case"],

    // Recommended built-in rules
    "no-var-keyword": true,
    "no-parameter-reassignment": true,
    "typedef": true,

    // Immutability rules
    "readonly-keyword": true,
    "readonly-array": true,
    "no-let": true,
    "no-object-mutation": true,
    "no-delete": true,
    "no-method-signature": true,

    // Functional style rules
    "no-mixed-interface": true
  }
}